rizz_wsgi/__init__.py
rizz_wsgi/api.py
rizz_wsgi/middleware.py
rizz_wsgi/request.py
rizz_wsgi/response.py
rizz_wsgi-0.0.5.dist-info/METADATA
rizz_wsgi-0.0.5.dist-info/WHEEL
rizz_wsgi-0.0.5.dist-info/top_level.txt
rizz_wsgi-0.0.5.dist-info/RECORD
