Metadata-Version: 2.1
Name: rizz-wsgi
Version: 0.0.5
Summary: Rizz is a Python web framework and can be used with any WSGI application server such as Gunicorn.
Author-email: Alex Kiura <kiuraalex@gmail.com>
Project-URL: Homepage, https://github.com/mrkiura/rizz
Classifier: Programming Language :: Python :: 3
Classifier: Operating System :: OS Independent
Requires-Python: >=3.10
Requires-Dist: Jinja2
Requires-Dist: parse
Requires-Dist: requests
Requires-Dist: requests-wsgi-adapter
Requires-Dist: WebOb
Requires-Dist: whitenoise
